newproject/__init__.py
newproject/_version.py
newproject/check.py
newproject/config/newproject_config.yaml
newproject/config/schema/json_schema.json
newproject/error_codes.py
newproject/error_logger.py
newproject/newproject.py
newproject/utils.py
newproject_cli-1.0.1.dist-info/LICENSE
newproject_cli-1.0.1.dist-info/METADATA
newproject_cli-1.0.1.dist-info/WHEEL
newproject_cli-1.0.1.dist-info/entry_points.txt
newproject_cli-1.0.1.dist-info/RECORD
