Metadata-Version: 2.1
Name: newproject-cli
Version: 1.0.1
Summary: A command-line tool to create new projects
Home-page: https://github.com/utox39/new-project-cli
License: MIT
Author: utox39
Author-email: francescomoccaldi39@gmail.com
Requires-Python: >=3.10
Classifier: Intended Audience :: Developers
Classifier: License :: OSI Approved :: MIT License
Classifier: Operating System :: MacOS
Classifier: Operating System :: Microsoft :: Windows
Classifier: Operating System :: Unix
Classifier: Programming Language :: Python :: 3
Classifier: Programming Language :: Python :: 3.10
Classifier: Programming Language :: Python :: 3.11
Classifier: Programming Language :: Python :: 3.12
Classifier: Topic :: Utilities
Requires-Dist: jsonschema (>=4.18.4)
Requires-Dist: pyyaml (>=6.0)
Requires-Dist: rich (>=13.4.2)
Requires-Dist: typer (>=0.9.0)
Requires-Dist: typing_extensions (>=4.7.0)
Project-URL: Bug Tracker, https://github.com/utox39/new-project-cli/issues
Project-URL: Repository, https://github.com/utox39/new-project-cli
